polygenic/__init__.py
polygenic/__main__.py
polygenic/pgstk.py
polygenic/version.py
polygenic/data/__init__.py
polygenic/data/csv_accessor.py
polygenic/data/data_accessor.py
polygenic/data/gwas.py
polygenic/data/gwas_data.py
polygenic/data/mobigen_utils.py
polygenic/data/polars_frame.py
polygenic/data/snp_data.py
polygenic/data/vcf_accessor.py
polygenic/data/vcf_record.py
polygenic/error/__init__.py
polygenic/error/polygenic_exception.py
polygenic/model/__init__.py
polygenic/model/model.py
polygenic/model/utils.py
polygenic/resources/chromsizes/hg38.chrom.sizes
polygenic/rsidx/__init__.py
polygenic/rsidx/__main__.py
polygenic/rsidx/_version.py
polygenic/rsidx/cli.py
polygenic/rsidx/index.py
polygenic/rsidx/search.py
polygenic/tools/__init__.py
polygenic/tools/gwasfilecreate.py
polygenic/tools/modelbiobankuk.py
polygenic/tools/modelgwasfile.py
polygenic/tools/modelpgscat.py
polygenic/tools/pgscompute.py
polygenic/tools/plotmanhattan.py
polygenic/tools/utils.py
polygenic/tools/vcfimpute.py
polygenic/tools/vcfindex.py
polygenic/tools/vcfstat.py
polygenic/tools/vcfstatbaf.py
polygenic/tools/vcfstatzygosity.py
polygenic/tools/data/__init__.py
polygenic/tools/data/chromsizes.py
polygenic/tools/data/colors.py
polygenic-2.3.17.dist-info/LICENSE
polygenic-2.3.17.dist-info/METADATA
polygenic-2.3.17.dist-info/WHEEL
polygenic-2.3.17.dist-info/entry_points.txt
polygenic-2.3.17.dist-info/top_level.txt
polygenic-2.3.17.dist-info/RECORD
