Metadata-Version: 2.1
Name: polygenic
Version: 2.3.17
Summary: Polygenic score toolkit
Home-page: https://github.com/marpiech/polygenic
Author: Marcin Piechota, Wojciech Galan
Author-email: piechota@intelliseq.com
License: Intelliseq dual licenses this package. For commercial use, please contact [contact @ intelliseq.com](mailto:contact@intelliseq.com). For non-commercial use, this license permits use of the software only by government agencies, schools, universities, non-profit organizations or individuals on projects that do not receive external funding other than government research grants and contracts. Any other use requires a commercial license. For the full license, please see [LICENSE.md](https://
Classifier: Development Status :: 5 - Production/Stable
Classifier: License :: Free for non-commercial use
Classifier: Programming Language :: Python :: 3
Classifier: Operating System :: Unix
Classifier: Operating System :: MacOS
Classifier: Topic :: Software Development :: Libraries :: Python Modules
Requires-Python: >=3.8
License-File: LICENSE
Requires-Dist: DotMap
Requires-Dist: importlib-resources
Requires-Dist: kaleido
Requires-Dist: logdecorator
Requires-Dist: numpy
Requires-Dist: pandas
Requires-Dist: plotly
Requires-Dist: plotnine
Requires-Dist: polars
Requires-Dist: progressbar2
Requires-Dist: pyarrow
Requires-Dist: pysam
Requires-Dist: pytabix
Requires-Dist: python-utils
Requires-Dist: pyyaml
Requires-Dist: scipy
Requires-Dist: tqdm
